{
"meta":{"test_sets":[],"test_metrics":[],"learn_metrics":[{"best_value":"Min","name":"Logloss"}],"launch_mode":"Train","parameters":"","iteration_count":200,"learn_sets":["learn"],"name":"experiment"},
"iterations":[
{"learn":[0.4336038028],"iteration":0,"passed_time":0.01938661021,"remaining_time":3.857935431},
{"learn":[0.2790002594],"iteration":1,"passed_time":0.03012026438,"remaining_time":2.981906173},
{"learn":[0.1850058729],"iteration":2,"passed_time":0.04384036045,"remaining_time":2.878850337},
{"learn":[0.1182131056],"iteration":3,"passed_time":0.06546040459,"remaining_time":3.207559825},
{"learn":[0.07692182614],"iteration":4,"passed_time":0.08875044247,"remaining_time":3.461267256},
{"learn":[0.0495324876],"iteration":5,"passed_time":0.1055969819,"remaining_time":3.414302413},
{"learn":[0.03423349224],"iteration":6,"passed_time":0.1276618533,"remaining_time":3.519819671},
{"learn":[0.02343800972],"iteration":7,"passed_time":0.1441706976,"remaining_time":3.460096742},
{"learn":[0.0162250985],"iteration":8,"passed_time":0.1576875577,"remaining_time":3.346480391},
{"learn":[0.0120531307],"iteration":9,"passed_time":0.1777579121,"remaining_time":3.377400329},
{"learn":[0.009159132231],"iteration":10,"passed_time":0.200922534,"remaining_time":3.452214448},
{"learn":[0.007095323646],"iteration":11,"passed_time":0.2204724224,"remaining_time":3.454067951},
{"learn":[0.005483090181],"iteration":12,"passed_time":0.2337139958,"remaining_time":3.36188594},
{"learn":[0.004451652536],"iteration":13,"passed_time":0.2529539575,"remaining_time":3.360674007},
{"learn":[0.003774208407],"iteration":14,"passed_time":0.2755522695,"remaining_time":3.398477991},
{"learn":[0.003153673845],"iteration":15,"passed_time":0.2917015416,"remaining_time":3.354567729},
{"learn":[0.002736585406],"iteration":16,"passed_time":0.313963448,"remaining_time":3.379724175},
{"learn":[0.002293402491],"iteration":17,"passed_time":0.3270157521,"remaining_time":3.306492604},
{"learn":[0.001950570154],"iteration":18,"passed_time":0.3400254748,"remaining_time":3.23919005},
{"learn":[0.001680783569],"iteration":19,"passed_time":0.3541930153,"remaining_time":3.187737138},
{"learn":[0.00149210333],"iteration":20,"passed_time":0.3725563729,"remaining_time":3.175599559},
{"learn":[0.001338889029],"iteration":21,"passed_time":0.3950657603,"remaining_time":3.196441151},
{"learn":[0.00120742075],"iteration":22,"passed_time":0.414683059,"remaining_time":3.191256585},
{"learn":[0.001099126086],"iteration":23,"passed_time":0.4335968696,"remaining_time":3.179710377},
{"learn":[0.001026098315],"iteration":24,"passed_time":0.4613881879,"remaining_time":3.229717316},
{"learn":[0.000957782776],"iteration":25,"passed_time":0.4889169263,"remaining_time":3.271982507},
{"learn":[0.0008830315641],"iteration":26,"passed_time":0.5111381534,"remaining_time":3.27507039},
{"learn":[0.0008179738267],"iteration":27,"passed_time":0.5327381341,"remaining_time":3.272534252},
{"learn":[0.0007467024379],"iteration":28,"passed_time":0.5468629803,"remaining_time":3.224605849},
{"learn":[0.0006869381615],"iteration":29,"passed_time":0.5662908101,"remaining_time":3.208981257},
{"learn":[0.0006514077489],"iteration":30,"passed_time":0.5912086208,"remaining_time":3.223040546},
{"learn":[0.0006060761632],"iteration":31,"passed_time":0.6122814545,"remaining_time":3.214477636},
{"learn":[0.0005642399778],"iteration":32,"passed_time":0.6305230136,"remaining_time":3.190828584},
{"learn":[0.0005343447009],"iteration":33,"passed_time":0.65049963,"remaining_time":3.175968782},
{"learn":[0.0005137775789],"iteration":34,"passed_time":0.6743125441,"remaining_time":3.178901994},
{"learn":[0.0004931110087],"iteration":35,"passed_time":0.6961083611,"remaining_time":3.171160311},
{"learn":[0.0004931007616],"iteration":36,"passed_time":0.720473433,"remaining_time":3.173977556},
{"learn":[0.0004930643306],"iteration":37,"passed_time":0.7443836908,"remaining_time":3.173425208},
{"learn":[0.000493054159],"iteration":38,"passed_time":0.7641778348,"remaining_time":3.154682857},
{"learn":[0.0004626631781],"iteration":39,"passed_time":0.778728612,"remaining_time":3.114914448},
{"learn":[0.0004354792678],"iteration":40,"passed_time":0.792887631,"remaining_time":3.074856911},
{"learn":[0.000417454412],"iteration":41,"passed_time":0.8160752207,"remaining_time":3.069997259},
{"learn":[0.0004174501069],"iteration":42,"passed_time":0.8376327876,"remaining_time":3.058333666},
{"learn":[0.0004058986071],"iteration":43,"passed_time":0.8613151205,"remaining_time":3.053753609},
{"learn":[0.0004058986071],"iteration":44,"passed_time":0.8826966233,"remaining_time":3.04039948},
{"learn":[0.0004058943113],"iteration":45,"passed_time":0.9000103177,"remaining_time":3.01307802},
{"learn":[0.000405877331],"iteration":46,"passed_time":0.923098973,"remaining_time":3.004981763},
{"learn":[0.0004058717322],"iteration":47,"passed_time":0.9378081241,"remaining_time":2.969725726},
{"learn":[0.0004058674369],"iteration":48,"passed_time":0.9545781836,"remaining_time":2.941659301},
{"learn":[0.0004058515102],"iteration":49,"passed_time":0.9757273031,"remaining_time":2.927181909},
{"learn":[0.0004057907695],"iteration":50,"passed_time":0.9973558309,"remaining_time":2.913843506},
{"learn":[0.0004057394225],"iteration":51,"passed_time":1.02056269,"remaining_time":2.904678425},
{"learn":[0.0004057394225],"iteration":52,"passed_time":1.04417436,"remaining_time":2.896106243},
{"learn":[0.0004057394225],"iteration":53,"passed_time":1.065372987,"remaining_time":2.880452892},
{"learn":[0.00040573513],"iteration":54,"passed_time":1.082132079,"remaining_time":2.852893663},
{"learn":[0.0004057308376],"iteration":55,"passed_time":1.098981249,"remaining_time":2.825951783},
{"learn":[0.0004057252426],"iteration":56,"passed_time":1.11216855,"remaining_time":2.790177239},
{"learn":[0.0004057252426],"iteration":57,"passed_time":1.134432352,"remaining_time":2.777403345},
{"learn":[0.000405660281],"iteration":58,"passed_time":1.158375976,"remaining_time":2.768322247},
{"learn":[0.0004055953409],"iteration":59,"passed_time":1.180056685,"remaining_time":2.753465598},
{"learn":[0.0004055653054],"iteration":60,"passed_time":1.207874033,"remaining_time":2.752368699},
{"learn":[0.00040549669],"iteration":61,"passed_time":1.228151128,"remaining_time":2.733626703},
{"learn":[0.0004054642451],"iteration":62,"passed_time":1.248858219,"remaining_time":2.715771048},
{"learn":[0.0004054642451],"iteration":63,"passed_time":1.272153071,"remaining_time":2.703325276},
{"learn":[0.0004054642451],"iteration":64,"passed_time":1.295894054,"remaining_time":2.691472267},
{"learn":[0.0004054642451],"iteration":65,"passed_time":1.31656055,"remaining_time":2.673016874},
{"learn":[0.0004054642451],"iteration":66,"passed_time":1.330038511,"remaining_time":2.6402257},
{"learn":[0.0004054642451],"iteration":67,"passed_time":1.353774574,"remaining_time":2.627915349},
{"learn":[0.0004054642451],"iteration":68,"passed_time":1.373749998,"remaining_time":2.608134054},
{"learn":[0.0004054642451],"iteration":69,"passed_time":1.386773944,"remaining_time":2.575437324},
{"learn":[0.0004054642451],"iteration":70,"passed_time":1.411066105,"remaining_time":2.563767994},
{"learn":[0.0004054642451],"iteration":71,"passed_time":1.428080276,"remaining_time":2.53880938},
{"learn":[0.0004054642451],"iteration":72,"passed_time":1.4479336,"remaining_time":2.51900777},
{"learn":[0.0003848298811],"iteration":73,"passed_time":1.466556484,"remaining_time":2.497109689},
{"learn":[0.0003848237912],"iteration":74,"passed_time":1.490590599,"remaining_time":2.484317666},
{"learn":[0.0003848164058],"iteration":75,"passed_time":1.508236135,"remaining_time":2.460806325},
{"learn":[0.0003848136751],"iteration":76,"passed_time":1.530430146,"remaining_time":2.444713091},
{"learn":[0.0003847878964],"iteration":77,"passed_time":1.555082046,"remaining_time":2.432307815},
{"learn":[0.0003847847621],"iteration":78,"passed_time":1.57818039,"remaining_time":2.417213002},
{"learn":[0.0003847715756],"iteration":79,"passed_time":1.599077748,"remaining_time":2.398616622},
{"learn":[0.0003847615247],"iteration":80,"passed_time":1.611789672,"remaining_time":2.367937914},
{"learn":[0.0003846811295],"iteration":81,"passed_time":1.624588955,"remaining_time":2.337823131},
{"learn":[0.0003846529258],"iteration":82,"passed_time":1.643932059,"remaining_time":2.317350011},
{"learn":[0.0003846471723],"iteration":83,"passed_time":1.668671994,"remaining_time":2.304356563},
{"learn":[0.0003846087622],"iteration":84,"passed_time":1.685071718,"remaining_time":2.279802912},
{"learn":[0.0003845932702],"iteration":85,"passed_time":1.701948136,"remaining_time":2.256070786},
{"learn":[0.0003845622631],"iteration":86,"passed_time":1.722998498,"remaining_time":2.237917589},
{"learn":[0.0003845421833],"iteration":87,"passed_time":1.7372485,"remaining_time":2.211043545},
{"learn":[0.0003844464239],"iteration":88,"passed_time":1.761240855,"remaining_time":2.196603762},
{"learn":[0.0003844429026],"iteration":89,"passed_time":1.781617099,"remaining_time":2.17753201},
{"learn":[0.0003844318507],"iteration":90,"passed_time":1.806019396,"remaining_time":2.163254002},
{"learn":[0.0003844288237],"iteration":91,"passed_time":1.830110525,"remaining_time":2.148390617},
{"learn":[0.0003844142283],"iteration":92,"passed_time":1.851781584,"remaining_time":2.130544403},
{"learn":[0.0003844107638],"iteration":93,"passed_time":1.872766361,"remaining_time":2.111842918},
{"learn":[0.0003844107638],"iteration":94,"passed_time":1.897465258,"remaining_time":2.097198443},
{"learn":[0.0003844043602],"iteration":95,"passed_time":1.921379707,"remaining_time":2.081494682},
{"learn":[0.000384365997],"iteration":96,"passed_time":1.93877328,"remaining_time":2.058697401},
{"learn":[0.0003843592514],"iteration":97,"passed_time":1.962680002,"remaining_time":2.04278939},
{"learn":[0.000384340074],"iteration":98,"passed_time":1.979724463,"remaining_time":2.019718896},
{"learn":[0.0003843367073],"iteration":99,"passed_time":2.003970147,"remaining_time":2.003970147},
{"learn":[0.000384287612],"iteration":100,"passed_time":2.028316466,"remaining_time":1.988151783},
{"learn":[0.0003842451989],"iteration":101,"passed_time":2.052762345,"remaining_time":1.972261861},
{"learn":[0.0003842415534],"iteration":102,"passed_time":2.072127615,"remaining_time":1.951421152},
{"learn":[0.0003842415534],"iteration":103,"passed_time":2.097450487,"remaining_time":1.936108142},
{"learn":[0.0003842355015],"iteration":104,"passed_time":2.120788998,"remaining_time":1.918809094},
{"learn":[0.000384223234],"iteration":105,"passed_time":2.146016904,"remaining_time":1.903071594},
{"learn":[0.000384219589],"iteration":106,"passed_time":2.166044327,"remaining_time":1.882636658},
{"learn":[0.0003842085517],"iteration":107,"passed_time":2.189353488,"remaining_time":1.865004823},
{"learn":[0.000384202506],"iteration":108,"passed_time":2.214068809,"remaining_time":1.848442767},
{"learn":[0.0003841441968],"iteration":109,"passed_time":2.233939084,"remaining_time":1.827768341},
{"learn":[0.0003840963134],"iteration":110,"passed_time":2.2585613,"remaining_time":1.81091852},
{"learn":[0.0003840907984],"iteration":111,"passed_time":2.282058722,"remaining_time":1.793046138},
{"learn":[0.0003840880585],"iteration":112,"passed_time":2.312695959,"remaining_time":1.780571225},
{"learn":[0.0003840823051],"iteration":113,"passed_time":2.341814871,"remaining_time":1.766632271},
{"learn":[0.0003840786629],"iteration":114,"passed_time":2.370302669,"remaining_time":1.751962842},
{"learn":[0.0003840678928],"iteration":115,"passed_time":2.405025262,"remaining_time":1.741570017},
{"learn":[0.0003840648287],"iteration":116,"passed_time":2.431150851,"remaining_time":1.72466257},
{"learn":[0.0003840538009],"iteration":117,"passed_time":2.459131559,"remaining_time":1.708888032},
{"learn":[0.0003840538009],"iteration":118,"passed_time":2.487236471,"remaining_time":1.692992892},
{"learn":[0.0003840538009],"iteration":119,"passed_time":2.521951797,"remaining_time":1.681301198},
{"learn":[0.0003840538009],"iteration":120,"passed_time":2.546440276,"remaining_time":1.662551916},
{"learn":[0.0003840538009],"iteration":121,"passed_time":2.573488173,"remaining_time":1.645344898},
{"learn":[0.0003840538009],"iteration":122,"passed_time":2.597735378,"remaining_time":1.626224586},
{"learn":[0.0003840538009],"iteration":123,"passed_time":2.623518475,"remaining_time":1.607962936},
{"learn":[0.0003840538009],"iteration":124,"passed_time":2.647932938,"remaining_time":1.588759763},
{"learn":[0.0003840538009],"iteration":125,"passed_time":2.67293924,"remaining_time":1.569821458},
{"learn":[0.0003840538009],"iteration":126,"passed_time":2.697208862,"remaining_time":1.550364149},
{"learn":[0.0003840538009],"iteration":127,"passed_time":2.724056518,"remaining_time":1.532281791},
{"learn":[0.0003840477552],"iteration":128,"passed_time":2.751636926,"remaining_time":1.514466835},
{"learn":[0.0003840477552],"iteration":129,"passed_time":2.776034249,"remaining_time":1.494787672},
{"learn":[0.0003840477552],"iteration":130,"passed_time":2.801628167,"remaining_time":1.475666744},
{"learn":[0.0003840477552],"iteration":131,"passed_time":2.827126967,"remaining_time":1.45639874},
{"learn":[0.0003840477552],"iteration":132,"passed_time":2.85775989,"remaining_time":1.439623403},
{"learn":[0.0003840477552],"iteration":133,"passed_time":2.882689719,"remaining_time":1.41983225},
{"learn":[0.0003840477552],"iteration":134,"passed_time":2.909866661,"remaining_time":1.401046911},
{"learn":[0.0003840477552],"iteration":135,"passed_time":2.933426653,"remaining_time":1.380436072},
{"learn":[0.0003840477552],"iteration":136,"passed_time":2.962412553,"remaining_time":1.362277305},
{"learn":[0.0003840477552],"iteration":137,"passed_time":2.990432959,"remaining_time":1.343527851},
{"learn":[0.0003839998831],"iteration":138,"passed_time":3.018126641,"remaining_time":1.32450162},
{"learn":[0.0003839998831],"iteration":139,"passed_time":3.045350809,"remaining_time":1.305150347},
{"learn":[0.0003839998831],"iteration":140,"passed_time":3.069876341,"remaining_time":1.284558185},
{"learn":[0.0003839998831],"iteration":141,"passed_time":3.094608219,"remaining_time":1.263994906},
{"learn":[0.0003839998831],"iteration":142,"passed_time":3.120112844,"remaining_time":1.243681343},
{"learn":[0.0003839998831],"iteration":143,"passed_time":3.145235992,"remaining_time":1.22314733},
{"learn":[0.0003839998831],"iteration":144,"passed_time":3.171278031,"remaining_time":1.202898564},
{"learn":[0.0003839998831],"iteration":145,"passed_time":3.194911078,"remaining_time":1.18167944},
{"learn":[0.0003839998831],"iteration":146,"passed_time":3.220880799,"remaining_time":1.161269948},
{"learn":[0.0003839998831],"iteration":147,"passed_time":3.244410831,"remaining_time":1.13992813},
{"learn":[0.0003839998831],"iteration":148,"passed_time":3.269525688,"remaining_time":1.119099396},
{"learn":[0.0003839998831],"iteration":149,"passed_time":3.292590188,"remaining_time":1.097530063},
{"learn":[0.0003839998831],"iteration":150,"passed_time":3.318103407,"remaining_time":1.076735543},
{"learn":[0.0003839998831],"iteration":151,"passed_time":3.34176805,"remaining_time":1.055295174},
{"learn":[0.0003839998831],"iteration":152,"passed_time":3.365936995,"remaining_time":1.033980646},
{"learn":[0.0003839998831],"iteration":153,"passed_time":3.389810386,"remaining_time":1.012540765},
{"learn":[0.0003839998831],"iteration":154,"passed_time":3.412779661,"remaining_time":0.9908069983},
{"learn":[0.0003839998831],"iteration":155,"passed_time":3.436862142,"remaining_time":0.9693713733},
{"learn":[0.0003839998831],"iteration":156,"passed_time":3.460496444,"remaining_time":0.9477792807},
{"learn":[0.0003839998831],"iteration":157,"passed_time":3.487050359,"remaining_time":0.9269374371},
{"learn":[0.0003839998831],"iteration":158,"passed_time":3.511252638,"remaining_time":0.905417347},
{"learn":[0.0003839998831],"iteration":159,"passed_time":3.537323705,"remaining_time":0.8843309261},
{"learn":[0.0003839998831],"iteration":160,"passed_time":3.563141021,"remaining_time":0.8631211168},
{"learn":[0.0003839998831],"iteration":161,"passed_time":3.589771643,"remaining_time":0.8420452003},
{"learn":[0.0003839998831],"iteration":162,"passed_time":3.613078612,"remaining_time":0.8201466789},
{"learn":[0.0003839998831],"iteration":163,"passed_time":3.638440786,"remaining_time":0.7986821237},
{"learn":[0.0003839998831],"iteration":164,"passed_time":3.661444256,"remaining_time":0.7766699936},
{"learn":[0.0003839998831],"iteration":165,"passed_time":3.685082228,"remaining_time":0.754775878},
{"learn":[0.0003839998831],"iteration":166,"passed_time":3.709685489,"remaining_time":0.7330516236},
{"learn":[0.0003839998831],"iteration":167,"passed_time":3.734005141,"remaining_time":0.7112390745},
{"learn":[0.0003839998831],"iteration":168,"passed_time":3.75806834,"remaining_time":0.6893498138},
{"learn":[0.0003839998831],"iteration":169,"passed_time":3.780802821,"remaining_time":0.6672004978},
{"learn":[0.0003839998831],"iteration":170,"passed_time":3.805289667,"remaining_time":0.6453415224},
{"learn":[0.0003839998831],"iteration":171,"passed_time":3.828356721,"remaining_time":0.6232208615},
{"learn":[0.0003839998831],"iteration":172,"passed_time":3.853382983,"remaining_time":0.6013950321},
{"learn":[0.0003839998831],"iteration":173,"passed_time":3.875947169,"remaining_time":0.5791645195},
{"learn":[0.0003839998831],"iteration":174,"passed_time":3.900075355,"remaining_time":0.5571536221},
{"learn":[0.0003839998831],"iteration":175,"passed_time":3.924725379,"remaining_time":0.5351898245},
{"learn":[0.0003839998831],"iteration":176,"passed_time":3.947769814,"remaining_time":0.512987038},
{"learn":[0.0003839998831],"iteration":177,"passed_time":3.971542626,"remaining_time":0.4908648189},
{"learn":[0.0003839998831],"iteration":178,"passed_time":3.993893986,"remaining_time":0.468557395},
{"learn":[0.0003839998831],"iteration":179,"passed_time":4.018002642,"remaining_time":0.446444738},
{"learn":[0.0003839998831],"iteration":180,"passed_time":4.043082812,"remaining_time":0.4244120079},
{"learn":[0.0003839998831],"iteration":181,"passed_time":4.070584008,"remaining_time":0.4025852316},
{"learn":[0.0003839998831],"iteration":182,"passed_time":4.093946023,"remaining_time":0.3803119256},
{"learn":[0.0003839998831],"iteration":183,"passed_time":4.119471153,"remaining_time":0.3582148828},
{"learn":[0.0003839998831],"iteration":184,"passed_time":4.14383041,"remaining_time":0.3359862495},
{"learn":[0.0003839998831],"iteration":185,"passed_time":4.168638337,"remaining_time":0.313768477},
{"learn":[0.0003839998831],"iteration":186,"passed_time":4.193057629,"remaining_time":0.2914959849},
{"learn":[0.0003839998831],"iteration":187,"passed_time":4.215926594,"remaining_time":0.2691016975},
{"learn":[0.0003839998831],"iteration":188,"passed_time":4.240905855,"remaining_time":0.2468252085},
{"learn":[0.0003839998831],"iteration":189,"passed_time":4.264170994,"remaining_time":0.2244300523},
{"learn":[0.0003839998831],"iteration":190,"passed_time":4.288978873,"remaining_time":0.2020984809},
{"learn":[0.0003839998831],"iteration":191,"passed_time":4.311601966,"remaining_time":0.1796500819},
{"learn":[0.0003839998831],"iteration":192,"passed_time":4.333854482,"remaining_time":0.157186432},
{"learn":[0.0003839998831],"iteration":193,"passed_time":4.35907162,"remaining_time":0.134816648},
{"learn":[0.0003839998831],"iteration":194,"passed_time":4.38339915,"remaining_time":0.11239485},
{"learn":[0.0003839998831],"iteration":195,"passed_time":4.407643399,"remaining_time":0.08995190609},
{"learn":[0.0003839998831],"iteration":196,"passed_time":4.431421561,"remaining_time":0.06748357708},
{"learn":[0.0003839998831],"iteration":197,"passed_time":4.455197469,"remaining_time":0.04500199464},
{"learn":[0.0003839998831],"iteration":198,"passed_time":4.477834288,"remaining_time":0.02250167984},
{"learn":[0.0003839998831],"iteration":199,"passed_time":4.500232218,"remaining_time":0}
]}